selene_classical_replay_plugin/__init__.py
selene_classical_replay_plugin/plugin.py
selene_classical_replay_plugin/py.typed
selene_classical_replay_plugin/_dist/lib/libselene_classical_replay.so
selene_coinflip_plugin/__init__.py
selene_coinflip_plugin/plugin.py
selene_coinflip_plugin/py.typed
selene_coinflip_plugin/_dist/lib/libselene_coinflip_plugin.so
selene_depolarizing_error_model_plugin/__init__.py
selene_depolarizing_error_model_plugin/plugin.py
selene_depolarizing_error_model_plugin/py.typed
selene_depolarizing_error_model_plugin/_dist/lib/libselene_depolarizing_plugin.so
selene_helios_qis_plugin/__init__.py
selene_helios_qis_plugin/build.py
selene_helios_qis_plugin/plugin.py
selene_helios_qis_plugin/py.typed
selene_helios_qis_plugin/_dist/include/helios_qis/cl_types.h
selene_helios_qis_plugin/_dist/include/helios_qis/interface.h
selene_helios_qis_plugin/_dist/lib/libhelios_selene_interface.a
selene_helios_qis_plugin/_dist/lib/libhelios_selene_interface_debug.a
selene_helios_qis_plugin/_dist/lib/libhelios_selene_interface_diagnostic.a
selene_helios_qis_plugin/_dist/lib64/cmake/HeliosSeleneInterface/HeliosSeleneInterfaceConfig.cmake
selene_helios_qis_plugin/_dist/lib64/cmake/HeliosSeleneInterface/HeliosSeleneInterfaceTargets-release.cmake
selene_helios_qis_plugin/_dist/lib64/cmake/HeliosSeleneInterface/HeliosSeleneInterfaceTargets.cmake
selene_ideal_error_model_plugin/__init__.py
selene_ideal_error_model_plugin/plugin.py
selene_ideal_error_model_plugin/py.typed
selene_ideal_error_model_plugin/_dist/lib/libselene_ideal_plugin.so
selene_quantum_replay_plugin/__init__.py
selene_quantum_replay_plugin/plugin.py
selene_quantum_replay_plugin/py.typed
selene_quantum_replay_plugin/_dist/lib/libselene_quantum_replay.so
selene_quest_plugin/__init__.py
selene_quest_plugin/plugin.py
selene_quest_plugin/py.typed
selene_quest_plugin/state.py
selene_quest_plugin/_dist/lib/libselene_quest_plugin.so
selene_sim/__init__.py
selene_sim-0.2.10.dist-info/METADATA
selene_sim-0.2.10.dist-info/WHEEL
selene_sim-0.2.10.dist-info/RECORD
selene_sim-0.2.10.dist-info/licenses/LICENSE
