Metadata-Version: 2.4
Name: selene-sim
Version: 0.2.10
Summary: Quantinuum's open source emulator for hybrid quantum computation
Project-URL: repository, https://github.com/quantinuum/selene
Author-email: Jake Arkinstall <jake.arkinstall@quantinuum.com>, TKET development team <tket-support@quantinuum.com>
Maintainer-email: Jake Arkinstall <jake.arkinstall@quantinuum.com>, TKET development team <tket-support@quantinuum.com>
License-File: LICENSE
Classifier: Development Status :: 4 - Beta
Classifier: Intended Audience :: Developers
Classifier: Intended Audience :: Science/Research
Classifier: License :: OSI Approved :: Apache Software License
Classifier: Programming Language :: Python :: Implementation :: CPython
Classifier: Programming Language :: Python :: Implementation :: PyPy
Classifier: Programming Language :: Rust
Classifier: Topic :: Scientific/Engineering :: Quantum Computing
Classifier: Topic :: System :: Emulators
Requires-Python: >=3.10
Requires-Dist: numpy>=2.2.6
Requires-Dist: pyyaml>=6.0.2
Requires-Dist: selene-core~=0.2.4
Requires-Dist: selene-hugr-qis-compiler~=0.2.6
Requires-Dist: tqdm>=4.67.1
